noodle/__init__.py
noodle/_noodle.py
noodle/hue.py
noodle/notebook.ipynb
noodle/types.py
noodle/utils.py
noodle-0.0.4.dist-info/METADATA
noodle-0.0.4.dist-info/WHEEL
noodle-0.0.4.dist-info/RECORD
