Metadata-Version: 2.1
Name: noodle
Version: 0.0.4
Summary: 
Author: Carlos
Author-email: carlos@pythoncheatsheet.org
Requires-Python: >=3.10,<4.0
Classifier: Programming Language :: Python :: 3
Classifier: Programming Language :: Python :: 3.10
Classifier: Programming Language :: Python :: 3.11
Requires-Dist: black (>=23.10.0,<24.0.0)
